meater/MeaterApi.py
meater/__init__.py
meater_python-0.0.8.dist-info/LICENSE
meater_python-0.0.8.dist-info/METADATA
meater_python-0.0.8.dist-info/WHEEL
meater_python-0.0.8.dist-info/top_level.txt
meater_python-0.0.8.dist-info/RECORD
