Metadata-Version: 2.1
Name: meater-python
Version: 0.0.8
Summary: A wrapper for the Apption Labs Meater probe API v1
Home-page: https://github.com/Sotolotl/meater-python
Author: Billy Stevenson
Author-email: meater-api@billystevenson.co.uk
License: UNKNOWN
Platform: UNKNOWN
Classifier: Programming Language :: Python :: 3
Classifier: License :: OSI Approved :: Apache Software License
Classifier: Operating System :: OS Independent
Requires-Python: >=3.6
